{"day positive rate": 0.83, "day neutral rate": 0.05, "day negative rate": 0.12, "day distri": {"0.7": 1, "0.99": 69, "0.71": 6, "0.81": 4, "0.97": 15, "0.91": 5, "0.98": 22, "1.0": 82, "0.95": 4, "0.8": 3, "0.72": 2, "0.96": 11, "0.17": 1, "0.89": 3, "0.04": 2, "0.77": 6, "0.94": 9, "0.67": 2, "0.25": 2, "0.9": 3, "0.23": 2, "0.59": 2, "0.53": 1, "0.62": 1, "0.92": 3, "0.86": 2, "0.78": 1, "0.61": 2, "0.16": 1, "0.0": 4, "0.73": 2, "0.43": 1, "0.79": 2, "0.34": 2, "0.31": 2, "0.41": 1, "0.75": 3, "0.21": 1, "0.83": 3, "0.88": 7, "0.45": 1, "0.64": 1, "0.11": 2, "0.07": 2, "0.08": 1, "0.2": 2, "0.02": 5, "0.82": 2, "0.42": 2, "0.33": 1, "0.13": 1, "0.93": 3, "0.85": 2, "0.84": 1, "0.65": 1, "0.56": 2, "0.69": 3, "0.03": 1, "0.14": 1, "0.4": 1, "0.38": 2, "0.22": 1, "0.49": 1, "0.01": 4, "0.12": 1, "0.44": 1, "0.15": 1, "0.39": 1, "0.46": 1, "0.87": 3, "0.18": 1, "0.74": 1, "0.58": 1, "0.05": 1, "0.63": 1, "0.68": 1, "0.51": 1}}